colorblind/__init__.py
colorblind/colorblind.py
colorblind-0.0.9.dist-info/LICENSE.txt
colorblind-0.0.9.dist-info/METADATA
colorblind-0.0.9.dist-info/WHEEL
colorblind-0.0.9.dist-info/top_level.txt
colorblind-0.0.9.dist-info/RECORD
