Metadata-Version: 2.1
Name: colorblind
Version: 0.0.9
Summary: A small example package
Home-page: https://gitlab.com/FloatFlow/colorblind
Author: floatflow
Author-email: wolfrahfeldt@gmail.com
License: UNKNOWN
Platform: UNKNOWN
Classifier: Programming Language :: Python :: 3
Classifier: License :: OSI Approved :: MIT License
Classifier: Operating System :: OS Independent
Requires-Python: >=3.6
